odoo_downloader/README.md
odoo_downloader/__init__.py
odoo_downloader/__meta__.py
odoo_downloader/__version__.py
odoo_downloader/downloader.py
odoo_downloader/odoo_downloader.ini
odoo_downloader/odoo_downloader.py
odoo_downloader-0.15.dist-info/LICENSE.rst
odoo_downloader-0.15.dist-info/METADATA
odoo_downloader-0.15.dist-info/WHEEL
odoo_downloader-0.15.dist-info/entry_points.txt
odoo_downloader-0.15.dist-info/top_level.txt
odoo_downloader-0.15.dist-info/RECORD
